amtokenizers/__init__.py
amtokenizers/params.py
amtokenizers/utils.py
amtokenizers/data/10000/10/byte_bpe/merges.txt
amtokenizers/data/10000/10/byte_bpe/vocab.json
amtokenizers/data/10000/10/char_bpe/merges.txt
amtokenizers/data/10000/10/char_bpe/vocab.json
amtokenizers/data/10000/10/sent_piece/merges.txt
amtokenizers/data/10000/10/sent_piece/vocab.json
amtokenizers/data/10000/10/word_piece/merges.txt
amtokenizers/data/10000/10/word_piece/vocab.json
amtokenizers/data/10000/5/byte_bpe/merges.txt
amtokenizers/data/10000/5/byte_bpe/vocab.json
amtokenizers/data/10000/5/char_bpe/merges.txt
amtokenizers/data/10000/5/char_bpe/vocab.json
amtokenizers/data/10000/5/sent_piece/merges.txt
amtokenizers/data/10000/5/sent_piece/vocab.json
amtokenizers/data/10000/5/word_piece/merges.txt
amtokenizers/data/10000/5/word_piece/vocab.json
amtokenizers/data/25000/10/byte_bpe/merges.txt
amtokenizers/data/25000/10/byte_bpe/vocab.json
amtokenizers/data/25000/10/char_bpe/merges.txt
amtokenizers/data/25000/10/char_bpe/vocab.json
amtokenizers/data/25000/10/sent_piece/merges.txt
amtokenizers/data/25000/10/sent_piece/vocab.json
amtokenizers/data/25000/10/word_piece/merges.txt
amtokenizers/data/25000/10/word_piece/vocab.json
amtokenizers/data/25000/5/byte_bpe/merges.txt
amtokenizers/data/25000/5/byte_bpe/vocab.json
amtokenizers/data/25000/5/char_bpe/merges.txt
amtokenizers/data/25000/5/char_bpe/vocab.json
amtokenizers/data/25000/5/sent_piece/merges.txt
amtokenizers/data/25000/5/sent_piece/vocab.json
amtokenizers/data/25000/5/word_piece/merges.txt
amtokenizers/data/25000/5/word_piece/vocab.json
amtokenizers/data/50000/10/byte_bpe/merges.txt
amtokenizers/data/50000/10/byte_bpe/vocab.json
amtokenizers/data/50000/10/char_bpe/merges.txt
amtokenizers/data/50000/10/char_bpe/vocab.json
amtokenizers/data/50000/10/sent_piece/merges.txt
amtokenizers/data/50000/10/sent_piece/vocab.json
amtokenizers/data/50000/10/word_piece/merges.txt
amtokenizers/data/50000/10/word_piece/vocab.json
amtokenizers-0.0.10.dist-info/METADATA
amtokenizers-0.0.10.dist-info/WHEEL
amtokenizers-0.0.10.dist-info/top_level.txt
amtokenizers-0.0.10.dist-info/RECORD
