Metadata-Version: 2.1
Name: amtokenizers
Version: 0.0.10
Summary: Amharic language tokenizers
Home-page: UNKNOWN
Author: Mitiku Yohannes
Author-email: se.mitiku.yohannes@gmail.com
License: MIT
Platform: UNKNOWN
Requires-Dist: transformers
